ediss/__init__.py
ediss/cipher.py
ediss/eddsa.py
ediss/keys.py
ediss/patch.py
ediss/utils.py
ediss-1.0.0.dist-info/LICENSE.txt
ediss-1.0.0.dist-info/METADATA
ediss-1.0.0.dist-info/WHEEL
ediss-1.0.0.dist-info/top_level.txt
ediss-1.0.0.dist-info/RECORD
