Metadata-Version: 2.1
Name: ediss
Version: 1.0.0
Summary: Integrated security scheme for curve25519.
Home-page: https://gitee.com/origamizyt/ediss
Author: origamizyt
Author-email: zhaoyitong18@163.com
License: UNKNOWN
Platform: UNKNOWN
Classifier: Programming Language :: Python :: 3
Classifier: License :: OSI Approved :: MIT License
Classifier: Operating System :: OS Independent
Requires-Python: >=3
Requires-Dist: cryptography
